jvc_projector/__init__.py
jvc_projector/commands.py
jvc_projector/jvc_projector.py
tests/__init__.py
tests/testLowLatency.py
jvc_projector_remote_improved2-3.7.2.dist-info/LICENSE
jvc_projector_remote_improved2-3.7.2.dist-info/METADATA
jvc_projector_remote_improved2-3.7.2.dist-info/WHEEL
jvc_projector_remote_improved2-3.7.2.dist-info/top_level.txt
jvc_projector_remote_improved2-3.7.2.dist-info/RECORD
